armis/__about__.py
armis/__init__.py
armis/armiscloud.py
armis-1.0.23.dist-info/METADATA
armis-1.0.23.dist-info/WHEEL
armis-1.0.23.dist-info/licenses/LICENSE.md
armis-1.0.23.dist-info/RECORD
