Metadata-Version: 2.3
Name: armis
Version: 1.0.23
Summary: Connect and perform actions with the Armis cloud
Project-URL: Homepage, https://github.com/mmlange/armis-python/
Project-URL: Issues, https://github.com/mmlange/armis-python/issues
Project-URL: Source, https://github.com/mmlange/armis-python/
Author-email: Matthew Lange <mmlange@gmail.com>
Maintainer-email: Matthew Lange <mmlange@gmail.com>
Keywords: api,armis,development
Classifier: Development Status :: 4 - Beta
Classifier: Intended Audience :: Developers
Classifier: License :: OSI Approved :: BSD License
Classifier: Programming Language :: Python :: 3
Classifier: Programming Language :: Python :: 3 :: Only
Classifier: Programming Language :: Python :: 3.9
Classifier: Programming Language :: Python :: 3.10
Classifier: Programming Language :: Python :: 3.11
Classifier: Programming Language :: Python :: 3.12
Classifier: Topic :: Communications
Classifier: Topic :: Software Development :: Libraries
Requires-Python: >=3.9
Requires-Dist: httpx[brotli,http2]==0.28.1
Requires-Dist: loguru==0.7.3
Requires-Dist: msgspec==0.18.6
Requires-Dist: pendulum==3.0.0
Requires-Dist: tenacity==9.0.0
